flask_cache_manifest/__init__.py
flask_cache_manifest/extension.py
flask_cache_manifest-1.0.4.dist-info/LICENSE
flask_cache_manifest-1.0.4.dist-info/METADATA
flask_cache_manifest-1.0.4.dist-info/WHEEL
flask_cache_manifest-1.0.4.dist-info/top_level.txt
flask_cache_manifest-1.0.4.dist-info/RECORD
